pylight_metrics/__init__.py
pylight_metrics/aggregator.py
pylight_metrics/core.py
pylight_metrics-0.2.0.dist-info/METADATA
pylight_metrics-0.2.0.dist-info/WHEEL
pylight_metrics-0.2.0.dist-info/RECORD
