Metadata-Version: 2.4
Name: pylight-metrics
Version: 0.2.0
Summary: A zero-contention, thread-safe metrics aggregator for high-performance Python applications.
Author-email: Mahesh Chandra <mahesh@example.com>
License: MIT
Classifier: License :: OSI Approved :: MIT License
Classifier: Operating System :: OS Independent
Classifier: Programming Language :: Python :: 3
Classifier: Topic :: System :: Monitoring
Requires-Python: >=3.8
